find_unicode_control/__init__.py
find_unicode_control/__main__.py
find_unicode_control/cli.py
find_unicode_control/find_unicode_control.py
find_unicode_control-0.1.1.dist-info/licenses/LICENSE
find_unicode_control-0.1.1.dist-info/METADATA
find_unicode_control-0.1.1.dist-info/WHEEL
find_unicode_control-0.1.1.dist-info/entry_points.txt
find_unicode_control-0.1.1.dist-info/top_level.txt
find_unicode_control-0.1.1.dist-info/RECORD
