Metadata-Version: 2.4
Name: find-unicode-control
Version: 0.1.1
Summary: Script to find Unicode control characters
Author: Siddhesh Poyarekar
Project-URL: Homepage, https://github.com/siddhesh/find-unicode-control
Keywords: unicode,script
Requires-Python: >=2.7
License-File: LICENSE
Dynamic: license-file
